retour_client/__init__.py
retour_client/adapters.py
retour_client/admin.py
retour_client/apps.py
retour_client/constantes.py
retour_client/context_processors.py
retour_client/http_utils.py
retour_client/urls.py
retour_client/forms/__init__.py
retour_client/forms/commentaires_bug.py
retour_client/forms/retour_client.py
retour_client/management/__init__.py
retour_client/management/envoi_mail_retour_client_preprod.py
retour_client/management/commands/__init__.py
retour_client/management/commands/envoi_mail_retour_client_preprod.py
retour_client/migrations/__init__.py
retour_client/models/__init__.py
retour_client/models/conversation_claude.py
retour_client/models/reponse_bug.py
retour_client/models/retour_client.py
retour_client/services/__init__.py
retour_client/services/claude_service.py
retour_client/services/statuts_bug.py
retour_client/templates/chatbot-sidebar.html
retour_client/templates/cockpit.html
retour_client/templates/detail-retour-client.html
retour_client/templates/formulaire_edition_modal.html
retour_client/templates/kanban-retour-client.html
retour_client/templates/liste-retour-client.html
retour_client/templates/pipeline-retour-client.html
retour_client/templates/recherche-filtre-bug.html
retour_client/templates/retour_client.html
retour_client/templates/css/kanban.css
retour_client/templates/css/pipeline.css
retour_client/templates/css/retour_client.css
retour_client/templates/mails/nouveau-ticket-client.tpl
retour_client/templates/mails/recap-journalier-client.tpl
retour_client/templates/mails/recap-journalier-revo.tpl
retour_client/templates/mails/reponse-ticket-client.tpl
retour_client/utils/__init__.py
retour_client/utils/anymail_utils.py
retour_client/views/__init__.py
retour_client/views/claude_views.py
retour_client/views/retour_client.py
module_retour_client_revo-1.1.6.dist-info/METADATA
module_retour_client_revo-1.1.6.dist-info/WHEEL
module_retour_client_revo-1.1.6.dist-info/RECORD
