Metadata-Version: 2.4
Name: module-retour-client-revo
Version: 1.1.6
Summary: Module Django pour la gestion des retours clients et bugs
Author-email: Revolucy <hello@revolucy.fr>
License: MIT
Classifier: Framework :: Django
Classifier: License :: OSI Approved :: MIT License
Classifier: Operating System :: OS Independent
Classifier: Programming Language :: Python :: 3
Classifier: Programming Language :: Python :: 3.10
Classifier: Programming Language :: Python :: 3.11
Classifier: Programming Language :: Python :: 3.12
Requires-Python: >=3.8
Requires-Dist: anthropic>=0.40.0
Requires-Dist: django-anymail[brevo]>=10.1
Requires-Dist: django<6.0,>=4.0
Requires-Dist: requests<3,>=2.31
